aiware/__init__.py
aiware/_internal/utils.py
aiware/_internal/generators/aiware_graphql.py
aiware/_internal/generators/aiware_search_types.py
aiware/_internal/generators/ariadne_plugin_init.py
aiware/_internal/generators/ariadne_plugin_stdlib_operation_names.py
aiware/aion/__init__.py
aiware/aion/_aion.py
aiware/client/__init__.py
aiware/client/async_client.py
aiware/client/async_client_ref.py
aiware/client/client.py
aiware/client/client_ref.py
aiware/client/sdo.py
aiware/client/search_models.py
aiware/client/test_client.py
aiware/client/test_clients_parity.py
aiware/client/utils.py
aiware/client/_base/async_base_client.py
aiware/client/_base/async_base_client_ref.py
aiware/client/_base/base_client.py
aiware/client/_base/base_client_ref.py
aiware/client/_base/base_model.py
aiware/client/_base/base_model_ref.py
aiware/client/_base/exceptions.py
aiware/client/_stdlib_generated/__init__.py
aiware/client/_stdlib_generated/async_base_client_ref.py
aiware/client/_stdlib_generated/async_client.py
aiware/client/_stdlib_generated/base_client_ref.py
aiware/client/_stdlib_generated/base_model_ref.py
aiware/client/_stdlib_generated/client.py
aiware/client/_stdlib_generated/create_sdo.py
aiware/client/_stdlib_generated/enums.py
aiware/client/_stdlib_generated/fragments.py
aiware/client/_stdlib_generated/get_schema.py
aiware/client/_stdlib_generated/get_sd_os.py
aiware/client/_stdlib_generated/get_sdo.py
aiware/client/_stdlib_generated/input_types.py
aiware/client/_stdlib_generated/search_types.py
aiware/client/_stdlib_generated/update_sdo.py
aiware/client/operations/CreateSDO.graphql
aiware/client/operations/GetSDO.graphql
aiware/client/operations/GetSDOs.graphql
aiware/client/operations/UpdateSDO.graphql
aiware/client/operations/_GetSchema.graphql
aiware/client/operations/fragments/SDO.graphql
aiware/client/operations/fragments/SDOPage.graphql
aiware/common/__init__.py
aiware/common/auth.py
aiware/common/schemas.py
aiware/common/sdo.py
aiware/common/utils.py
aiware-0.4.0.dist-info/METADATA
aiware-0.4.0.dist-info/WHEEL
aiware-0.4.0.dist-info/entry_points.txt
aiware-0.4.0.dist-info/RECORD
