Metadata-Version: 2.4
Name: aiware
Version: 0.4.0
Summary: Add your description here
Requires-Python: >=3.12
Requires-Dist: ariadne-codegen>=0.14.0
Requires-Dist: datamodel-code-generator>=0.33.0
Requires-Dist: jsonschema>=4.25.1
Requires-Dist: pydantic>=2.11
Requires-Dist: python-dotenv>=1.1.0
Requires-Dist: python-magic>=0.4.27
Requires-Dist: requests>=2.32.5
